dynatrace/metric/utils/__init__.py
dynatrace/metric/utils/_dynatrace_metadata_enricher.py
dynatrace/metric/utils/_metric.py
dynatrace/metric/utils/_metric_values.py
dynatrace/metric/utils/_normalize.py
dynatrace/metric/utils/dynatrace_metrics_api_constants.py
dynatrace/metric/utils/dynatrace_metrics_factory.py
dynatrace/metric/utils/dynatrace_metrics_serializer.py
dynatrace/metric/utils/metric_error.py
dynatrace_metric_utils-0.2.1.dist-info/LICENSE
dynatrace_metric_utils-0.2.1.dist-info/METADATA
dynatrace_metric_utils-0.2.1.dist-info/WHEEL
dynatrace_metric_utils-0.2.1.dist-info/entry_points.txt
dynatrace_metric_utils-0.2.1.dist-info/top_level.txt
dynatrace_metric_utils-0.2.1.dist-info/RECORD
