Metadata-Version: 2.1
Name: dynatrace-metric-utils
Version: 0.2.1
Summary: Dynatrace Metric Utilities
Home-page: https://github.com/dynatrace-oss/dynatrace-metric-utils-python
Author: Dynatrace
Author-email: opensource@dynatrace.com
License: Apache-2.0
Project-URL: Dynatrace, https://www.dynatrace.com/
Project-URL: Source, https://github.com/dynatrace-oss/dynatrace-metric-utils-python
Project-URL: Download, https://pypi.org/project/dynatrace-metric-utils/#files
Platform: any
Classifier: Development Status :: 5 - Production/Stable
Classifier: Intended Audience :: Developers
Classifier: License :: OSI Approved :: Apache Software License
Classifier: Operating System :: OS Independent
Classifier: Programming Language :: Python
Classifier: Programming Language :: Python :: 3
Classifier: Programming Language :: Python :: 3.7
Classifier: Programming Language :: Python :: 3.8
Classifier: Programming Language :: Python :: 3.9
Classifier: Programming Language :: Python :: 3.10
Classifier: Programming Language :: Python :: Implementation :: CPython
Classifier: Programming Language :: Python :: Implementation :: PyPy
Classifier: Topic :: System :: Monitoring
Requires-Python: >=3.7
